[
  {
    "id": "p001",
    "name": "Person 01",
    "birth": 1920,
    "death": 1990,
    "spouse": "p002",
    "parents": [],
    "children": ["p003", "p004", "p005"],
    "photo": "Photos/Default.jpg"
  },
  {
    "id": "p002",
    "name": "Person 02",
    "birth": 1925,
    "death": 1995,
    "spouse": "p001",
    "parents": [],
    "children": ["p003", "p004", "p005"],
    "photo": "Photos/Default.jpg"
  },
  {
    "id": "p003",
    "name": "Person 03",
    "birth": 1948,
    "death": null,
    "spouse": "p006",
    "parents": ["p001", "p002"],
    "children": ["p007", "p008"],
    "photo": "Photos/Default.jpg"
  },
  {
    "id": "p004",
    "name": "Person 04",
    "birth": 1950,
    "death": null,
    "spouse": "p009",
    "parents": ["p001", "p002"],
    "children": ["p010", "p011"],
    "photo": "Photos/Default.jpg"
  },
  {
    "id": "p005",
    "name": "Person 05",
    "birth": 1955,
    "death": null,
    "spouse": "p012",
    "parents": ["p001", "p002"],
    "children": ["p013"],
    "photo": "Photos/Default.jpg"
  },
  {
    "id": "p006",
    "name": "Person 06",
    "birth": 1950,
    "death": null,
    "spouse": "p003",
    "parents": ["p033","p034"],
    "children": ["p007", "p008"],
    "photo": "Photos/Default.jpg"
  },
  {
    "id": "p007",
    "name": "Person 07",
    "birth": 1975,
    "death": null,
    "spouse": "p014",
    "parents": ["p003", "p006"],
    "children": ["p015", "p016"],
    "photo": "Photos/Default.jpg"
  },
  {
    "id": "p008",
    "name": "Person 08",
    "birth": 1978,
    "death": null,
    "spouse": null,
    "parents": ["p003", "p006"],
    "children": [],
    "photo": "Photos/Default.jpg"
  },
  {
    "id": "p009",
    "name": "Person 09",
    "birth": 1945,
    "death": 2010,
    "spouse": "p004",
    "parents": [],
    "children": ["p010", "p011"],
    "photo": "Photos/Default.jpg"
  },
  {
    "id": "p010",
    "name": "Person 10",
    "birth": 1972,
    "death": null,
    "spouse": "p017",
    "parents": ["p004", "p009"],
    "children": ["p018"],
    "photo": "Photos/Default.jpg"
  },
  {
    "id": "p011",
    "name": "Person 11",
    "birth": 1974,
    "death": null,
    "spouse": null,
    "parents": ["p004", "p009"],
    "children": [],
    "photo": "Photos/Default.jpg"
  },
  {
    "id": "p012",
    "name": "Person 12",
    "birth": 1960,
    "death": null,
    "spouse": "p005",
    "parents": [],
    "children": ["p013"],
    "photo": "Photos/Default.jpg"
  },
  {
    "id": "p013",
    "name": "Person 13",
    "birth": 1985,
    "death": null,
    "spouse": null,
    "parents": ["p005", "p012"],
    "children": [],
    "photo": "Photos/Default.jpg"
  },
  {
    "id": "p014",
    "name": "Person 14",
    "birth": 1977,
    "death": null,
    "spouse": "p007",
    "parents": [],
    "children": ["p015", "p016"],
    "photo": "Photos/Default.jpg"
  },
  {
    "id": "p015",
    "name": "Person 15",
    "birth": 2002,
    "death": null,
    "spouse": null,
    "parents": ["p007", "p014"],
    "children": [],
    "photo": "Photos/Default.jpg"
  },
  {
    "id": "p016",
    "name": "Person 16",
    "birth": 2005,
    "death": null,
    "spouse": null,
    "parents": ["p007", "p014"],
    "children": [],
    "photo": "Photos/Default.jpg"
  },
  {
    "id": "p017",
    "name": "Person 17",
    "birth": 1970,
    "death": null,
    "spouse": "p010",
    "parents": [],
    "children": ["p018"],
    "photo": "Photos/Default.jpg"
  },
  {
    "id": "p018",
    "name": "Person 18",
    "birth": 2000,
    "death": null,
    "spouse": null,
    "parents": ["p010", "p017"],
    "children": [],
    "photo": "Photos/Default.jpg"
  },
  {
    "id": "p019",
    "name": "Person 19",
    "birth": 1965,
    "death": null,
    "spouse": "p020",
    "parents": [],
    "children": ["p021", "p022"],
    "photo": "Photos/Default.jpg"
  },
  {
    "id": "p020",
    "name": "Person 20",
    "birth": 1967,
    "death": null,
    "spouse": "p019",
    "parents": [],
    "children": ["p021", "p022"],
    "photo": "Photos/Default.jpg"
  },
  {
    "id": "p021",
    "name": "Person 21",
    "birth": 1990,
    "death": null,
    "spouse": null,
    "parents": ["p019", "p020"],
    "children": [],
    "photo": "Photos/Default.jpg"
  },
  {
    "id": "p022",
    "name": "Person 22",
    "birth": 1992,
    "death": null,
    "spouse": null,
    "parents": ["p019", "p020"],
    "children": [],
    "photo": "Photos/Default.jpg"
  },
  {
    "id": "p023",
    "name": "Person 23",
    "birth": 1950,
    "death": null,
    "spouse": "p024",
    "parents": [],
    "children": ["p025"],
    "photo": "Photos/Default.jpg"
  },
  {
    "id": "p024",
    "name": "Person 24",
    "birth": 1952,
    "death": null,
    "spouse": "p023",
    "parents": [],
    "children": ["p025"],
    "photo": "Photos/Default.jpg"
  },
  {
    "id": "p025",
    "name": "Person 25",
    "birth": 1980,
    "death": null,
    "spouse": "p026",
    "parents": ["p023", "p024"],
    "children": ["p027"],
    "photo": "Photos/Default.jpg"
  },
  {
    "id": "p026",
    "name": "Person 26",
    "birth": 1979,
    "death": null,
    "spouse": "p025",
    "parents": [],
    "children": ["p027"],
    "photo": "Photos/Default.jpg"
  },
  {
    "id": "p027",
    "name": "Person 27",
    "birth": 2008,
    "death": null,
    "spouse": null,
    "parents": ["p025", "p026"],
    "children": [],
    "photo": "Photos/Default.jpg"
  },
  {
    "id": "p028",
    "name": "Person 28",
    "birth": 1960,
    "death": null,
    "spouse": null,
    "parents": [],
    "children": [],
    "photo": "Photos/Default.jpg"
  },
  {
    "id": "p029",
    "name": "Person 29",
    "birth": 1963,
    "death": null,
    "spouse": null,
    "parents": [],
    "children": [],
    "photo": "Photos/Default.jpg"
  },
  {
    "id": "p030",
    "name": "Person 30",
    "birth": 1940,
    "death": 2010,
    "spouse": "p031",
    "parents": [],
    "children": ["p032"],
    "photo": "Photos/Default.jpg"
  },
  {
    "id": "p031",
    "name": "Person 31",
    "birth": 1942,
    "death": 2015,
    "spouse": "p030",
    "parents": [],
    "children": ["p032"],
    "photo": "Photos/Default.jpg"
  },
  {
    "id": "p032",
    "name": "Person 32",
    "birth": 1970,
    "death": null,
    "spouse": null,
    "parents": ["p030", "p031"],
    "children": [],
    "photo": "Photos/Default.jpg"
  },
  {
    "id": "p033",
    "name": "Person 33",
    "birth": 1970,
    "death": null,
    "spouse": "p034",
    "parents": [],
    "children": ["p006"],
    "photo": "Photos/Default.jpg"
  },
  {
    "id": "p034",
    "name": "Person 34",
    "birth": 1970,
    "death": null,
    "spouse": "p033",
    "parents": [],
    "children": ["p006"],
    "photo": "Photos/Default.jpg"
  }
]
